JianZhiOfferTijieJeancheng/README.md
JianZhiOfferTijieJeancheng/__init__.py
JianZhiOfferTijieJeancheng/__main__.py
JianZhiOfferTijieJeancheng/file.epub
JianZhiOfferTijieJeancheng/index.html
JianZhiOfferTijieJeancheng/css/__init__.py
JianZhiOfferTijieJeancheng/css/annotations.css
JianZhiOfferTijieJeancheng/css/main.css
JianZhiOfferTijieJeancheng/css/normalize.css
JianZhiOfferTijieJeancheng/css/popup.css
JianZhiOfferTijieJeancheng/font/__init__.py
JianZhiOfferTijieJeancheng/font/fontello.eot
JianZhiOfferTijieJeancheng/font/fontello.svg
JianZhiOfferTijieJeancheng/font/fontello.ttf
JianZhiOfferTijieJeancheng/font/fontello.woff
JianZhiOfferTijieJeancheng/img/__init__.py
JianZhiOfferTijieJeancheng/img/annotator-glyph-sprite.png
JianZhiOfferTijieJeancheng/img/annotator-icon-sprite.png
JianZhiOfferTijieJeancheng/img/apple-touch-icon.png
JianZhiOfferTijieJeancheng/img/cancelfullscreen.png
JianZhiOfferTijieJeancheng/img/close.png
JianZhiOfferTijieJeancheng/img/fullscreen.png
JianZhiOfferTijieJeancheng/img/loader.gif
JianZhiOfferTijieJeancheng/img/menu-icon.png
JianZhiOfferTijieJeancheng/img/save.png
JianZhiOfferTijieJeancheng/img/saved.png
JianZhiOfferTijieJeancheng/img/settings-s.png
JianZhiOfferTijieJeancheng/img/settings.png
JianZhiOfferTijieJeancheng/img/star.png
JianZhiOfferTijieJeancheng/js/__init__.py
JianZhiOfferTijieJeancheng/js/epub.js
JianZhiOfferTijieJeancheng/js/epub.min.js
JianZhiOfferTijieJeancheng/js/epub.min.map
JianZhiOfferTijieJeancheng/js/hooks.min.js
JianZhiOfferTijieJeancheng/js/hooks.min.map
JianZhiOfferTijieJeancheng/js/reader.js
JianZhiOfferTijieJeancheng/js/reader.js.map
JianZhiOfferTijieJeancheng/js/reader.min.js
JianZhiOfferTijieJeancheng/js/reader.min.map
JianZhiOfferTijieJeancheng/js/hooks/__init__.py
JianZhiOfferTijieJeancheng/js/hooks/extensions/__init__.py
JianZhiOfferTijieJeancheng/js/hooks/extensions/highlight.js
JianZhiOfferTijieJeancheng/js/libs/__init__.py
JianZhiOfferTijieJeancheng/js/libs/jquery.min.js
jian_zhi_offer_tijie_jeancheng-2024.3.2.0.dist-info/METADATA
jian_zhi_offer_tijie_jeancheng-2024.3.2.0.dist-info/WHEEL
jian_zhi_offer_tijie_jeancheng-2024.3.2.0.dist-info/entry_points.txt
jian_zhi_offer_tijie_jeancheng-2024.3.2.0.dist-info/top_level.txt
jian_zhi_offer_tijie_jeancheng-2024.3.2.0.dist-info/RECORD
